vdsql/__about__.py
vdsql/__init__.py
vdsql/__main__.py
vdsql/_ibis.py
vdsql/bigquery.py
vdsql/clickhouse.py
vdsql/ibis.py
vdsql/snowflake.py
vdsql-0.2.dist-info/LICENSE-apache2.txt
vdsql-0.2.dist-info/METADATA
vdsql-0.2.dist-info/WHEEL
vdsql-0.2.dist-info/entry_points.txt
vdsql-0.2.dist-info/top_level.txt
vdsql-0.2.dist-info/RECORD
