Metadata-Version: 2.1
Name: vdsql
Version: 0.2
Summary: VisiData for database queries
Home-page: https://github.com/visidata/vdsql
Author: Saul Pwanson
Keywords: visidata sql rdbms ibis substrait
Classifier: Development Status :: 4 - Beta
Classifier: Programming Language :: Python :: 3
Requires-Python: >=3.8
License-File: LICENSE-apache2.txt
Requires-Dist: visidata (>=2.10.2)
Requires-Dist: clickhouse-driver[numpy] (>=0.2.4)
Requires-Dist: ibis-framework[clickhouse,sqlite] (>=3.2)
Requires-Dist: ibis-substrait
Requires-Dist: sqlparse
Requires-Dist: ibis-bigquery
